<Properties StartupConfiguration="{FE2B1805-6F2D-4C66-961A-BAFA0AD2F296}|https">
  <MonoDevelop.Ide.Workspace ActiveConfiguration="Debug" />
  <MonoDevelop.Ide.ItemProperties.Zoo.Api PreferredExecutionTarget="/Applications/Google Chrome.app" />
  <MonoDevelop.Ide.DebuggingService.PinnedWatches />
  <MonoDevelop.Ide.DebuggingService.Breakpoints>
    <BreakpointStore />
  </MonoDevelop.Ide.DebuggingService.Breakpoints>
  <MultiItemStartupConfigurations />
  <MonoDevelop.Ide.ItemProperties.Zoo.Presentation FirstBuild="True" />
  <MonoDevelop.Ide.Workbench ActiveDocument="Zoo.Presentation/Program.cs">
    <Files>
      <File FileName="Zoo.Presentation/Program.cs" Line="1" Column="1" />
    </Files>
    <Pads>
      <Pad Id="ProjectPad">
        <State name="__root__">
          <Node name="ZooManagement" expanded="True">
            <Node name="Zoo.Presentation" expanded="True" />
          </Node>
        </State>
      </Pad>
      <Pad Id="MonoDevelop.UnitTesting.TestPad">
        <State name="__root__">
          <Node name="ZooManagement" selected="True" />
        </State>
      </Pad>
    </Pads>
  </MonoDevelop.Ide.Workbench>
</Properties>